COPYRIGHT.txt
LICENSE.txt
MANIFEST.in
README.rst
buildout.cfg
setup.cfg
setup.py
docs/HISTORY.txt
z3c/__init__.py
z3c.soap.egg-info/PKG-INFO
z3c.soap.egg-info/SOURCES.txt
z3c.soap.egg-info/dependency_links.txt
z3c.soap.egg-info/namespace_packages.txt
z3c.soap.egg-info/not-zip-safe
z3c.soap.egg-info/requires.txt
z3c.soap.egg-info/top_level.txt
z3c/soap/HTTPRequest.py
z3c/soap/README.txt
z3c/soap/__init__.py
z3c/soap/configure.zcml
z3c/soap/ftesting.zcml
z3c/soap/ftests.py
z3c/soap/interfaces.py
z3c/soap/mem.txt
z3c/soap/meta.zcml
z3c/soap/metaconfigure.py
z3c/soap/metadirectives.py
z3c/soap/patch.py
z3c/soap/publisher.py
z3c/soap/soap.py
z3c/soap/tests/__init__.py
z3c/soap/tests/mailvalidation.py
z3c/soap/tests/soap.zcml
z3c/soap/tests/soap212.zcml
z3c/soap/tests/soap_error.zcml
z3c/soap/tests/test_directives.py
z3c/soap/tests/test_soappublication.py
z3c/soap/tests/test_soaprequest.py