Metadata-Version: 1.1
Name: z3c.soap
Version: 0.5.5
Summary: Soap using ZSI in Zope 2
Home-page: https://github.com/zopefoundation/z3c.soap
Author: Jean-Francois Roche
Author-email: jfroche@affinitic.be
License: ZPL 2.1
Keywords: Zope2 SOAP ZSI
Platform: UNKNOWN
Classifier: Environment :: Web Environment
Classifier: Framework :: Zope2
Classifier: Framework :: Zope3
Classifier: License :: OSI Approved :: Zope Public License
Classifier: Operating System :: OS Independent
Classifier: Programming Language :: Python
Classifier: Topic :: Internet :: WWW/HTTP :: Site Management
Classifier: Topic :: Software Development :: Libraries :: Python Modules
